dbrownell_DevTools/BuildActivities.py
dbrownell_DevTools/PythonBuildActivities.py
dbrownell_DevTools/__init__.py
dbrownell_DevTools/RepoBuildTools/Python.py
dbrownell_DevTools/RepoBuildTools/__init__.py
dbrownell_DevTools/Scripts/Output2Markdown.py
dbrownell_DevTools/Scripts/ShowScripts.py
dbrownell_DevTools/Scripts/__init__.py
dbrownell_DevTools/Scripts/CommitEmojis/__init__.py
dbrownell_DevTools/Scripts/CommitEmojis/__main__.py
dbrownell_DevTools/Scripts/CommitEmojis/categories.json
dbrownell_DevTools/Scripts/CommitEmojis/Gitmoji/gitmojis.json
dbrownell_DevTools/Scripts/CommitEmojis/Gitmoji/schema.json
dbrownell_DevTools/Scripts/CommitEmojis/Gitmoji/update_data.py
dbrownell_DevTools/Scripts/Python/MatchTests.py
dbrownell_DevTools/Scripts/Python/VSCodeTests.py
dbrownell_DevTools/Scripts/Python/__init__.py
dbrownell_devtools-0.19.10.dist-info/licenses/LICENSE.txt
dbrownell_devtools-0.19.10.dist-info/METADATA
dbrownell_devtools-0.19.10.dist-info/WHEEL
dbrownell_devtools-0.19.10.dist-info/entry_points.txt
dbrownell_devtools-0.19.10.dist-info/top_level.txt
dbrownell_devtools-0.19.10.dist-info/RECORD
